{"_ts":[1564666904],"_r":{"breakdown":{"html":{"bytes":[44871],"requests":[9]},"js":{"bytes":[1039791],"requests":[30]},"css":{"bytes":[128081],"requests":[2]},"image":{"bytes":[534935],"requests":[59]},"flash":{"bytes":[0],"requests":[0]},"font":{"bytes":[106988],"requests":[5]},"video":{"bytes":[0],"requests":[0]},"other":{"bytes":[986],"requests":[7]}},"date":[1564666904],"domElements":[1115],"domInteractive":[1959],"firstPaint":[1761.9350000004],"fullyLoaded":[4949],"id":["190801_YC_75d989272aab802e9064b197b7ecdf58"],"loadTime":[2],"render":[1800],"SpeedIndex":[2092],"TTFB":[154],"videoFrames":[[{"_i":"ms_000000.jpg","_t":0,"_vc":0},{"_i":"ms_001800.jpg","_t":1800,"_vc":5},{"_i":"ms_001900.jpg","_t":1900,"_vc":27},{"_i":"ms_002000.jpg","_t":2000,"_vc":84},{"_i":"ms_002100.jpg","_t":2100,"_vc":84},{"_i":"ms_002200.jpg","_t":2200,"_vc":84},{"_i":"ms_002400.jpg","_t":2400,"_vc":88},{"_i":"ms_002500.jpg","_t":2500,"_vc":91},{"_i":"ms_002600.jpg","_t":2600,"_vc":95},{"_i":"ms_003200.jpg","_t":3200,"_vc":99},{"_i":"ms_003300.jpg","_t":3300,"_vc":99},{"_i":"ms_003700.jpg","_t":3700,"_vc":99},{"_i":"ms_004100.jpg","_t":4100,"_vc":100},{"_i":"ms_004400.jpg","_t":4400,"_vc":100}]],"visualComplete":[4100],"lighthouse":[27],"pagespeed":[61]}}